[{"name":"sql.active_record","payload":{"sql":"SELECT  \"users\".* FROM \"users\"  WHERE \"users\".\"id\" = 3 LIMIT 1","name":"User Load","connection_id":49242384,"binds":[],"line":36,"filename":"C:/Sites/work/tulkit/app/views/jobs/index.html.erb","method":"_app_views_jobs_index_html_erb___552676019_53062752"},"time":"2014-05-29T23:20:28-04:00","transaction_id":"534a8b4a7dabf06bc5b7","end":"2014-05-29T23:20:28-04:00","children":[],"duration":1.9980000000000002},{"name":"sql.active_record","payload":{"sql":"SELECT  \"jobs\".* FROM \"jobs\"   ORDER BY \"jobs\".\"updated_at\" DESC LIMIT 1","name":"Job Load","connection_id":49242384,"binds":[],"line":21,"filename":"C:/Sites/work/tulkit/app/models/job.rb","method":"latest"},"time":"2014-05-29T23:20:28-04:00","transaction_id":"534a8b4a7dabf06bc5b7","end":"2014-05-29T23:20:28-04:00","children":[],"duration":1.9989999999999999},{"name":"sql.active_record","payload":{"sql":"SELECT \"jobs\".* FROM \"jobs\"  WHERE \"jobs\".\"status\" = 't'  ORDER BY \"jobs\".\"updated_at\" DESC","name":"Job Load","connection_id":49242384,"binds":[],"line":74,"filename":"C:/Sites/work/tulkit/app/views/jobs/index.html.erb","method":"block in _app_views_jobs_index_html_erb___552676019_53062752"},"time":"2014-05-29T23:20:28-04:00","transaction_id":"534a8b4a7dabf06bc5b7","end":"2014-05-29T23:20:28-04:00","children":[],"duration":2.996},{"name":"sql.active_record","payload":{"sql":"SELECT \"categories\".* FROM \"categories\"   ORDER BY \"categories\".\"lft\" ASC","name":"Category Load","connection_id":49242384,"binds":[],"line":154,"filename":"C:/Sites/work/tulkit/app/views/jobs/index.html.erb","method":"_app_views_jobs_index_html_erb___552676019_53062752"},"time":"2014-05-29T23:20:28-04:00","transaction_id":"534a8b4a7dabf06bc5b7","end":"2014-05-29T23:20:28-04:00","children":[],"duration":1.9980000000000002},{"name":"sql.active_record","payload":{"sql":"SELECT COUNT(*) FROM \"jobs\"  WHERE \"jobs\".\"status\" = 't' AND \"jobs\".\"category_id\" = 5","name":null,"connection_id":49242384,"binds":[],"line":158,"filename":"C:/Sites/work/tulkit/app/views/jobs/index.html.erb","method":"block in _app_views_jobs_index_html_erb___552676019_53062752"},"time":"2014-05-29T23:20:28-04:00","transaction_id":"534a8b4a7dabf06bc5b7","end":"2014-05-29T23:20:28-04:00","children":[],"duration":1.001},{"name":"sql.active_record","payload":{"sql":"SELECT \"categories\".* FROM \"categories\"  WHERE \"categories\".\"parent_id\" = 5  ORDER BY \"categories\".\"lft\" ASC","name":"Category Load","connection_id":49242384,"binds":[],"line":160,"filename":"C:/Sites/work/tulkit/app/views/jobs/index.html.erb","method":"block in _app_views_jobs_index_html_erb___552676019_53062752"},"time":"2014-05-29T23:20:28-04:00","transaction_id":"534a8b4a7dabf06bc5b7","end":"2014-05-29T23:20:28-04:00","children":[],"duration":2.009},{"name":"sql.active_record","payload":{"sql":"SELECT COUNT(*) FROM \"jobs\"  WHERE \"jobs\".\"status\" = 't' AND \"jobs\".\"category_id\" = 6","name":null,"connection_id":49242384,"binds":[],"line":161,"filename":"C:/Sites/work/tulkit/app/views/jobs/index.html.erb","method":"block (2 levels) in _app_views_jobs_index_html_erb___552676019_53062752"},"time":"2014-05-29T23:20:28-04:00","transaction_id":"534a8b4a7dabf06bc5b7","end":"2014-05-29T23:20:28-04:00","children":[],"duration":3.9709999999999996},{"name":"sql.active_record","payload":{"sql":"SELECT COUNT(*) FROM \"jobs\"  WHERE \"jobs\".\"status\" = 't' AND \"jobs\".\"category_id\" = 7","name":null,"connection_id":49242384,"binds":[],"line":161,"filename":"C:/Sites/work/tulkit/app/views/jobs/index.html.erb","method":"block (2 levels) in _app_views_jobs_index_html_erb___552676019_53062752"},"time":"2014-05-29T23:20:28-04:00","transaction_id":"534a8b4a7dabf06bc5b7","end":"2014-05-29T23:20:28-04:00","children":[],"duration":1.996},{"name":"sql.active_record","payload":{"sql":"SELECT COUNT(*) FROM \"jobs\"  WHERE \"jobs\".\"status\" = 't' AND \"jobs\".\"category_id\" = 8","name":null,"connection_id":49242384,"binds":[],"line":161,"filename":"C:/Sites/work/tulkit/app/views/jobs/index.html.erb","method":"block (2 levels) in _app_views_jobs_index_html_erb___552676019_53062752"},"time":"2014-05-29T23:20:28-04:00","transaction_id":"534a8b4a7dabf06bc5b7","end":"2014-05-29T23:20:28-04:00","children":[],"duration":1.002},{"name":"sql.active_record","payload":{"sql":"SELECT COUNT(*) FROM \"jobs\"  WHERE \"jobs\".\"status\" = 't' AND \"jobs\".\"category_id\" = 5","binds":[],"name":"CACHE","connection_id":49242384,"line":189,"filename":"C:/Sites/work/tulkit/app/views/jobs/index.html.erb","method":"block in _app_views_jobs_index_html_erb___552676019_53062752"},"time":"2014-05-29T23:20:28-04:00","transaction_id":"0ae8f5e67693b087af12","end":"2014-05-29T23:20:28-04:00","children":[],"duration":0.998},{"name":"sql.active_record","payload":{"sql":"SELECT  \"categories\".* FROM \"categories\"  WHERE \"categories\".\"id\" = ?  ORDER BY \"categories\".\"id\" ASC LIMIT 1","name":"Category Load","connection_id":49242384,"binds":[[{"name":"id","sql_type":"INTEGER","null":false,"limit":null,"precision":null,"scale":null,"type":"integer","default":null,"default_function":null,"primary":null,"coder":null},5]],"line":191,"filename":"C:/Sites/work/tulkit/app/views/jobs/index.html.erb","method":"block (2 levels) in _app_views_jobs_index_html_erb___552676019_53062752"},"time":"2014-05-29T23:20:28-04:00","transaction_id":"534a8b4a7dabf06bc5b7","end":"2014-05-29T23:20:28-04:00","children":[],"duration":1.9980000000000002},{"name":"sql.active_record","payload":{"sql":"SELECT COUNT(*) FROM \"jobs\"  WHERE \"jobs\".\"status\" = 't' AND \"jobs\".\"category_id\" = 6","binds":[],"name":"CACHE","connection_id":49242384,"line":192,"filename":"C:/Sites/work/tulkit/app/views/jobs/index.html.erb","method":"block (2 levels) in _app_views_jobs_index_html_erb___552676019_53062752"},"time":"2014-05-29T23:20:28-04:00","transaction_id":"0ae8f5e67693b087af12","end":"2014-05-29T23:20:28-04:00","children":[],"duration":0.9990000000000001},{"name":"sql.active_record","payload":{"sql":"SELECT  \"categories\".* FROM \"categories\"  WHERE \"categories\".\"id\" = ?  ORDER BY \"categories\".\"id\" ASC LIMIT 1","binds":[[{"name":"id","sql_type":"INTEGER","null":false,"limit":null,"precision":null,"scale":null,"type":"integer","default":null,"default_function":null,"primary":null,"coder":null},5]],"name":"CACHE","connection_id":49242384,"line":191,"filename":"C:/Sites/work/tulkit/app/views/jobs/index.html.erb","method":"block (2 levels) in _app_views_jobs_index_html_erb___552676019_53062752"},"time":"2014-05-29T23:20:28-04:00","transaction_id":"0ae8f5e67693b087af12","end":"2014-05-29T23:20:28-04:00","children":[],"duration":1.0},{"name":"sql.active_record","payload":{"sql":"SELECT COUNT(*) FROM \"jobs\"  WHERE \"jobs\".\"status\" = 't' AND \"jobs\".\"category_id\" = 7","binds":[],"name":"CACHE","connection_id":49242384,"line":192,"filename":"C:/Sites/work/tulkit/app/views/jobs/index.html.erb","method":"block (2 levels) in _app_views_jobs_index_html_erb___552676019_53062752"},"time":"2014-05-29T23:20:28-04:00","transaction_id":"0ae8f5e67693b087af12","end":"2014-05-29T23:20:28-04:00","children":[],"duration":1.9989999999999999},{"name":"sql.active_record","payload":{"sql":"SELECT  \"categories\".* FROM \"categories\"  WHERE \"categories\".\"id\" = ?  ORDER BY \"categories\".\"id\" ASC LIMIT 1","binds":[[{"name":"id","sql_type":"INTEGER","null":false,"limit":null,"precision":null,"scale":null,"type":"integer","default":null,"default_function":null,"primary":null,"coder":null},5]],"name":"CACHE","connection_id":49242384,"line":191,"filename":"C:/Sites/work/tulkit/app/views/jobs/index.html.erb","method":"block (2 levels) in _app_views_jobs_index_html_erb___552676019_53062752"},"time":"2014-05-29T23:20:28-04:00","transaction_id":"0ae8f5e67693b087af12","end":"2014-05-29T23:20:28-04:00","children":[],"duration":1.9120000000000001},{"name":"sql.active_record","payload":{"sql":"SELECT COUNT(*) FROM \"jobs\"  WHERE \"jobs\".\"status\" = 't' AND \"jobs\".\"category_id\" = 8","binds":[],"name":"CACHE","connection_id":49242384,"line":192,"filename":"C:/Sites/work/tulkit/app/views/jobs/index.html.erb","method":"block (2 levels) in _app_views_jobs_index_html_erb___552676019_53062752"},"time":"2014-05-29T23:20:28-04:00","transaction_id":"0ae8f5e67693b087af12","end":"2014-05-29T23:20:28-04:00","children":[],"duration":1.0},{"name":"sql.active_record","payload":{"sql":"SELECT  \"categories\".* FROM \"categories\"  WHERE \"categories\".\"id\" = ?  ORDER BY \"categories\".\"id\" ASC LIMIT 1","name":"Category Load","connection_id":49242384,"binds":[[{"name":"id","sql_type":"INTEGER","null":false,"limit":null,"precision":null,"scale":null,"type":"integer","default":null,"default_function":null,"primary":null,"coder":null},19]],"line":191,"filename":"C:/Sites/work/tulkit/app/views/jobs/index.html.erb","method":"block (2 levels) in _app_views_jobs_index_html_erb___552676019_53062752"},"time":"2014-05-29T23:20:28-04:00","transaction_id":"534a8b4a7dabf06bc5b7","end":"2014-05-29T23:20:28-04:00","children":[],"duration":1.9989999999999999},{"name":"sql.active_record","payload":{"sql":"SELECT  \"categories\".* FROM \"categories\"  WHERE \"categories\".\"id\" = ?  ORDER BY \"categories\".\"id\" ASC LIMIT 1","binds":[[{"name":"id","sql_type":"INTEGER","null":false,"limit":null,"precision":null,"scale":null,"type":"integer","default":null,"default_function":null,"primary":null,"coder":null},19]],"name":"CACHE","connection_id":49242384,"line":191,"filename":"C:/Sites/work/tulkit/app/views/jobs/index.html.erb","method":"block (2 levels) in _app_views_jobs_index_html_erb___552676019_53062752"},"time":"2014-05-29T23:20:28-04:00","transaction_id":"0ae8f5e67693b087af12","end":"2014-05-29T23:20:28-04:00","children":[],"duration":1.889},{"name":"sql.active_record","payload":{"sql":"SELECT  \"categories\".* FROM \"categories\"  WHERE \"categories\".\"id\" = ?  ORDER BY \"categories\".\"id\" ASC LIMIT 1","binds":[[{"name":"id","sql_type":"INTEGER","null":false,"limit":null,"precision":null,"scale":null,"type":"integer","default":null,"default_function":null,"primary":null,"coder":null},19]],"name":"CACHE","connection_id":49242384,"line":191,"filename":"C:/Sites/work/tulkit/app/views/jobs/index.html.erb","method":"block (2 levels) in _app_views_jobs_index_html_erb___552676019_53062752"},"time":"2014-05-29T23:20:28-04:00","transaction_id":"0ae8f5e67693b087af12","end":"2014-05-29T23:20:28-04:00","children":[],"duration":1.0},{"name":"sql.active_record","payload":{"sql":"SELECT  \"categories\".* FROM \"categories\"  WHERE \"categories\".\"id\" = ?  ORDER BY \"categories\".\"id\" ASC LIMIT 1","name":"Category Load","connection_id":49242384,"binds":[[{"name":"id","sql_type":"INTEGER","null":false,"limit":null,"precision":null,"scale":null,"type":"integer","default":null,"default_function":null,"primary":null,"coder":null},25]],"line":191,"filename":"C:/Sites/work/tulkit/app/views/jobs/index.html.erb","method":"block (2 levels) in _app_views_jobs_index_html_erb___552676019_53062752"},"time":"2014-05-29T23:20:28-04:00","transaction_id":"534a8b4a7dabf06bc5b7","end":"2014-05-29T23:20:28-04:00","children":[],"duration":1.9200000000000002},{"name":"sql.active_record","payload":{"sql":"SELECT  \"categories\".* FROM \"categories\"  WHERE \"categories\".\"id\" = ?  ORDER BY \"categories\".\"id\" ASC LIMIT 1","binds":[[{"name":"id","sql_type":"INTEGER","null":false,"limit":null,"precision":null,"scale":null,"type":"integer","default":null,"default_function":null,"primary":null,"coder":null},25]],"name":"CACHE","connection_id":49242384,"line":191,"filename":"C:/Sites/work/tulkit/app/views/jobs/index.html.erb","method":"block (2 levels) in _app_views_jobs_index_html_erb___552676019_53062752"},"time":"2014-05-29T23:20:28-04:00","transaction_id":"0ae8f5e67693b087af12","end":"2014-05-29T23:20:28-04:00","children":[],"duration":0.969},{"name":"sql.active_record","payload":{"sql":"SELECT  \"categories\".* FROM \"categories\"  WHERE \"categories\".\"id\" = ?  ORDER BY \"categories\".\"id\" ASC LIMIT 1","binds":[[{"name":"id","sql_type":"INTEGER","null":false,"limit":null,"precision":null,"scale":null,"type":"integer","default":null,"default_function":null,"primary":null,"coder":null},25]],"name":"CACHE","connection_id":49242384,"line":191,"filename":"C:/Sites/work/tulkit/app/views/jobs/index.html.erb","method":"block (2 levels) in _app_views_jobs_index_html_erb___552676019_53062752"},"time":"2014-05-29T23:20:28-04:00","transaction_id":"0ae8f5e67693b087af12","end":"2014-05-29T23:20:28-04:00","children":[],"duration":1.0},{"name":"sql.active_record","payload":{"sql":"SELECT COUNT(*) FROM \"jobs\"  WHERE \"jobs\".\"status\" = 't' AND \"jobs\".\"category_id\" = 9","name":null,"connection_id":49242384,"binds":[],"line":158,"filename":"C:/Sites/work/tulkit/app/views/jobs/index.html.erb","method":"block in _app_views_jobs_index_html_erb___552676019_53062752"},"time":"2014-05-29T23:20:28-04:00","transaction_id":"534a8b4a7dabf06bc5b7","end":"2014-05-29T23:20:28-04:00","children":[],"duration":1.001},{"name":"sql.active_record","payload":{"sql":"SELECT \"categories\".* FROM \"categories\"  WHERE \"categories\".\"parent_id\" = 9  ORDER BY \"categories\".\"lft\" ASC","name":"Category Load","connection_id":49242384,"binds":[],"line":160,"filename":"C:/Sites/work/tulkit/app/views/jobs/index.html.erb","method":"block in _app_views_jobs_index_html_erb___552676019_53062752"},"time":"2014-05-29T23:20:28-04:00","transaction_id":"534a8b4a7dabf06bc5b7","end":"2014-05-29T23:20:28-04:00","children":[],"duration":1.9989999999999999},{"name":"sql.active_record","payload":{"sql":"SELECT COUNT(*) FROM \"jobs\"  WHERE \"jobs\".\"status\" = 't' AND \"jobs\".\"category_id\" = 9","binds":[],"name":"CACHE","connection_id":49242384,"line":189,"filename":"C:/Sites/work/tulkit/app/views/jobs/index.html.erb","method":"block in _app_views_jobs_index_html_erb___552676019_53062752"},"time":"2014-05-29T23:20:28-04:00","transaction_id":"0ae8f5e67693b087af12","end":"2014-05-29T23:20:28-04:00","children":[],"duration":1.891},{"name":"sql.active_record","payload":{"sql":"SELECT COUNT(*) FROM \"jobs\"  WHERE \"jobs\".\"status\" = 't' AND \"jobs\".\"category_id\" = 10","name":null,"connection_id":49242384,"binds":[],"line":158,"filename":"C:/Sites/work/tulkit/app/views/jobs/index.html.erb","method":"block in _app_views_jobs_index_html_erb___552676019_53062752"},"time":"2014-05-29T23:20:28-04:00","transaction_id":"534a8b4a7dabf06bc5b7","end":"2014-05-29T23:20:28-04:00","children":[],"duration":2.0},{"name":"sql.active_record","payload":{"sql":"SELECT \"categories\".* FROM \"categories\"  WHERE \"categories\".\"parent_id\" = 10  ORDER BY \"categories\".\"lft\" ASC","name":"Category Load","connection_id":49242384,"binds":[],"line":160,"filename":"C:/Sites/work/tulkit/app/views/jobs/index.html.erb","method":"block in _app_views_jobs_index_html_erb___552676019_53062752"},"time":"2014-05-29T23:20:28-04:00","transaction_id":"534a8b4a7dabf06bc5b7","end":"2014-05-29T23:20:28-04:00","children":[],"duration":1.001},{"name":"sql.active_record","payload":{"sql":"SELECT COUNT(*) FROM \"jobs\"  WHERE \"jobs\".\"status\" = 't' AND \"jobs\".\"category_id\" = 10","binds":[],"name":"CACHE","connection_id":49242384,"line":189,"filename":"C:/Sites/work/tulkit/app/views/jobs/index.html.erb","method":"block in _app_views_jobs_index_html_erb___552676019_53062752"},"time":"2014-05-29T23:20:28-04:00","transaction_id":"0ae8f5e67693b087af12","end":"2014-05-29T23:20:28-04:00","children":[],"duration":1.002},{"name":"sql.active_record","payload":{"sql":"SELECT COUNT(*) FROM \"jobs\"  WHERE \"jobs\".\"status\" = 't' AND \"jobs\".\"category_id\" = 11","name":null,"connection_id":49242384,"binds":[],"line":158,"filename":"C:/Sites/work/tulkit/app/views/jobs/index.html.erb","method":"block in _app_views_jobs_index_html_erb___552676019_53062752"},"time":"2014-05-29T23:20:28-04:00","transaction_id":"534a8b4a7dabf06bc5b7","end":"2014-05-29T23:20:28-04:00","children":[],"duration":1.9949999999999999},{"name":"sql.active_record","payload":{"sql":"SELECT \"categories\".* FROM \"categories\"  WHERE \"categories\".\"parent_id\" = 11  ORDER BY \"categories\".\"lft\" ASC","name":"Category Load","connection_id":49242384,"binds":[],"line":160,"filename":"C:/Sites/work/tulkit/app/views/jobs/index.html.erb","method":"block in _app_views_jobs_index_html_erb___552676019_53062752"},"time":"2014-05-29T23:20:28-04:00","transaction_id":"534a8b4a7dabf06bc5b7","end":"2014-05-29T23:20:28-04:00","children":[],"duration":0.9970000000000001},{"name":"sql.active_record","payload":{"sql":"SELECT COUNT(*) FROM \"jobs\"  WHERE \"jobs\".\"status\" = 't' AND \"jobs\".\"category_id\" = 11","binds":[],"name":"CACHE","connection_id":49242384,"line":189,"filename":"C:/Sites/work/tulkit/app/views/jobs/index.html.erb","method":"block in _app_views_jobs_index_html_erb___552676019_53062752"},"time":"2014-05-29T23:20:28-04:00","transaction_id":"0ae8f5e67693b087af12","end":"2014-05-29T23:20:28-04:00","children":[],"duration":0.9990000000000001},{"name":"sql.active_record","payload":{"sql":"SELECT COUNT(*) FROM \"jobs\"  WHERE \"jobs\".\"status\" = 't' AND \"jobs\".\"category_id\" = 14","name":null,"connection_id":49242384,"binds":[],"line":158,"filename":"C:/Sites/work/tulkit/app/views/jobs/index.html.erb","method":"block in _app_views_jobs_index_html_erb___552676019_53062752"},"time":"2014-05-29T23:20:28-04:00","transaction_id":"534a8b4a7dabf06bc5b7","end":"2014-05-29T23:20:28-04:00","children":[],"duration":1.996},{"name":"sql.active_record","payload":{"sql":"SELECT \"categories\".* FROM \"categories\"  WHERE \"categories\".\"parent_id\" = 14  ORDER BY \"categories\".\"lft\" ASC","name":"Category Load","connection_id":49242384,"binds":[],"line":160,"filename":"C:/Sites/work/tulkit/app/views/jobs/index.html.erb","method":"block in _app_views_jobs_index_html_erb___552676019_53062752"},"time":"2014-05-29T23:20:28-04:00","transaction_id":"534a8b4a7dabf06bc5b7","end":"2014-05-29T23:20:28-04:00","children":[],"duration":2.0},{"name":"sql.active_record","payload":{"sql":"SELECT COUNT(*) FROM \"jobs\"  WHERE \"jobs\".\"status\" = 't' AND \"jobs\".\"category_id\" = 14","binds":[],"name":"CACHE","connection_id":49242384,"line":189,"filename":"C:/Sites/work/tulkit/app/views/jobs/index.html.erb","method":"block in _app_views_jobs_index_html_erb___552676019_53062752"},"time":"2014-05-29T23:20:28-04:00","transaction_id":"0ae8f5e67693b087af12","end":"2014-05-29T23:20:28-04:00","children":[],"duration":0.998},{"name":"sql.active_record","payload":{"sql":"SELECT COUNT(*) FROM \"jobs\"  WHERE \"jobs\".\"status\" = 't' AND \"jobs\".\"category_id\" = 15","name":null,"connection_id":49242384,"binds":[],"line":158,"filename":"C:/Sites/work/tulkit/app/views/jobs/index.html.erb","method":"block in _app_views_jobs_index_html_erb___552676019_53062752"},"time":"2014-05-29T23:20:28-04:00","transaction_id":"534a8b4a7dabf06bc5b7","end":"2014-05-29T23:20:28-04:00","children":[],"duration":2.999},{"name":"sql.active_record","payload":{"sql":"SELECT \"categories\".* FROM \"categories\"  WHERE \"categories\".\"parent_id\" = 15  ORDER BY \"categories\".\"lft\" ASC","name":"Category Load","connection_id":49242384,"binds":[],"line":160,"filename":"C:/Sites/work/tulkit/app/views/jobs/index.html.erb","method":"block in _app_views_jobs_index_html_erb___552676019_53062752"},"time":"2014-05-29T23:20:28-04:00","transaction_id":"534a8b4a7dabf06bc5b7","end":"2014-05-29T23:20:28-04:00","children":[],"duration":1.002},{"name":"sql.active_record","payload":{"sql":"SELECT COUNT(*) FROM \"jobs\"  WHERE \"jobs\".\"status\" = 't' AND \"jobs\".\"category_id\" = 15","binds":[],"name":"CACHE","connection_id":49242384,"line":189,"filename":"C:/Sites/work/tulkit/app/views/jobs/index.html.erb","method":"block in _app_views_jobs_index_html_erb___552676019_53062752"},"time":"2014-05-29T23:20:28-04:00","transaction_id":"0ae8f5e67693b087af12","end":"2014-05-29T23:20:28-04:00","children":[],"duration":1.0},{"name":"sql.active_record","payload":{"sql":"SELECT COUNT(*) FROM \"jobs\"  WHERE \"jobs\".\"status\" = 't' AND \"jobs\".\"category_id\" = 16","name":null,"connection_id":49242384,"binds":[],"line":158,"filename":"C:/Sites/work/tulkit/app/views/jobs/index.html.erb","method":"block in _app_views_jobs_index_html_erb___552676019_53062752"},"time":"2014-05-29T23:20:28-04:00","transaction_id":"534a8b4a7dabf06bc5b7","end":"2014-05-29T23:20:28-04:00","children":[],"duration":1.997},{"name":"sql.active_record","payload":{"sql":"SELECT \"categories\".* FROM \"categories\"  WHERE \"categories\".\"parent_id\" = 16  ORDER BY \"categories\".\"lft\" ASC","name":"Category Load","connection_id":49242384,"binds":[],"line":160,"filename":"C:/Sites/work/tulkit/app/views/jobs/index.html.erb","method":"block in _app_views_jobs_index_html_erb___552676019_53062752"},"time":"2014-05-29T23:20:28-04:00","transaction_id":"534a8b4a7dabf06bc5b7","end":"2014-05-29T23:20:28-04:00","children":[],"duration":2.0},{"name":"sql.active_record","payload":{"sql":"SELECT COUNT(*) FROM \"jobs\"  WHERE \"jobs\".\"status\" = 't' AND \"jobs\".\"category_id\" = 16","binds":[],"name":"CACHE","connection_id":49242384,"line":189,"filename":"C:/Sites/work/tulkit/app/views/jobs/index.html.erb","method":"block in _app_views_jobs_index_html_erb___552676019_53062752"},"time":"2014-05-29T23:20:28-04:00","transaction_id":"0ae8f5e67693b087af12","end":"2014-05-29T23:20:28-04:00","children":[],"duration":1.001},{"name":"sql.active_record","payload":{"sql":"SELECT COUNT(*) FROM \"jobs\"  WHERE \"jobs\".\"status\" = 't' AND \"jobs\".\"category_id\" = 17","name":null,"connection_id":49242384,"binds":[],"line":158,"filename":"C:/Sites/work/tulkit/app/views/jobs/index.html.erb","method":"block in _app_views_jobs_index_html_erb___552676019_53062752"},"time":"2014-05-29T23:20:28-04:00","transaction_id":"534a8b4a7dabf06bc5b7","end":"2014-05-29T23:20:28-04:00","children":[],"duration":1.002},{"name":"sql.active_record","payload":{"sql":"SELECT \"categories\".* FROM \"categories\"  WHERE \"categories\".\"parent_id\" = 17  ORDER BY \"categories\".\"lft\" ASC","name":"Category Load","connection_id":49242384,"binds":[],"line":160,"filename":"C:/Sites/work/tulkit/app/views/jobs/index.html.erb","method":"block in _app_views_jobs_index_html_erb___552676019_53062752"},"time":"2014-05-29T23:20:28-04:00","transaction_id":"534a8b4a7dabf06bc5b7","end":"2014-05-29T23:20:28-04:00","children":[],"duration":1.898},{"name":"sql.active_record","payload":{"sql":"SELECT COUNT(*) FROM \"jobs\"  WHERE \"jobs\".\"status\" = 't' AND \"jobs\".\"category_id\" = 17","binds":[],"name":"CACHE","connection_id":49242384,"line":189,"filename":"C:/Sites/work/tulkit/app/views/jobs/index.html.erb","method":"block in _app_views_jobs_index_html_erb___552676019_53062752"},"time":"2014-05-29T23:20:28-04:00","transaction_id":"0ae8f5e67693b087af12","end":"2014-05-29T23:20:28-04:00","children":[],"duration":0.9970000000000001},{"name":"sql.active_record","payload":{"sql":"SELECT COUNT(*) FROM \"jobs\"  WHERE \"jobs\".\"status\" = 't' AND \"jobs\".\"category_id\" = 18","name":null,"connection_id":49242384,"binds":[],"line":158,"filename":"C:/Sites/work/tulkit/app/views/jobs/index.html.erb","method":"block in _app_views_jobs_index_html_erb___552676019_53062752"},"time":"2014-05-29T23:20:28-04:00","transaction_id":"534a8b4a7dabf06bc5b7","end":"2014-05-29T23:20:28-04:00","children":[],"duration":1.002},{"name":"sql.active_record","payload":{"sql":"SELECT \"categories\".* FROM \"categories\"  WHERE \"categories\".\"parent_id\" = 18  ORDER BY \"categories\".\"lft\" ASC","name":"Category Load","connection_id":49242384,"binds":[],"line":160,"filename":"C:/Sites/work/tulkit/app/views/jobs/index.html.erb","method":"block in _app_views_jobs_index_html_erb___552676019_53062752"},"time":"2014-05-29T23:20:28-04:00","transaction_id":"534a8b4a7dabf06bc5b7","end":"2014-05-29T23:20:28-04:00","children":[],"duration":1.9989999999999999},{"name":"sql.active_record","payload":{"sql":"SELECT COUNT(*) FROM \"jobs\"  WHERE \"jobs\".\"status\" = 't' AND \"jobs\".\"category_id\" = 18","binds":[],"name":"CACHE","connection_id":49242384,"line":189,"filename":"C:/Sites/work/tulkit/app/views/jobs/index.html.erb","method":"block in _app_views_jobs_index_html_erb___552676019_53062752"},"time":"2014-05-29T23:20:28-04:00","transaction_id":"0ae8f5e67693b087af12","end":"2014-05-29T23:20:28-04:00","children":[],"duration":0.885},{"name":"sql.active_record","payload":{"sql":"SELECT COUNT(*) FROM \"jobs\"  WHERE \"jobs\".\"status\" = 't' AND \"jobs\".\"category_id\" = 19","name":null,"connection_id":49242384,"binds":[],"line":158,"filename":"C:/Sites/work/tulkit/app/views/jobs/index.html.erb","method":"block in _app_views_jobs_index_html_erb___552676019_53062752"},"time":"2014-05-29T23:20:28-04:00","transaction_id":"534a8b4a7dabf06bc5b7","end":"2014-05-29T23:20:28-04:00","children":[],"duration":2.911},{"name":"sql.active_record","payload":{"sql":"SELECT \"categories\".* FROM \"categories\"  WHERE \"categories\".\"parent_id\" = 19  ORDER BY \"categories\".\"lft\" ASC","name":"Category Load","connection_id":49242384,"binds":[],"line":160,"filename":"C:/Sites/work/tulkit/app/views/jobs/index.html.erb","method":"block in _app_views_jobs_index_html_erb___552676019_53062752"},"time":"2014-05-29T23:20:28-04:00","transaction_id":"534a8b4a7dabf06bc5b7","end":"2014-05-29T23:20:28-04:00","children":[],"duration":1.996},{"name":"sql.active_record","payload":{"sql":"SELECT COUNT(*) FROM \"jobs\"  WHERE \"jobs\".\"status\" = 't' AND \"jobs\".\"category_id\" = 20","name":null,"connection_id":49242384,"binds":[],"line":161,"filename":"C:/Sites/work/tulkit/app/views/jobs/index.html.erb","method":"block (2 levels) in _app_views_jobs_index_html_erb___552676019_53062752"},"time":"2014-05-29T23:20:28-04:00","transaction_id":"534a8b4a7dabf06bc5b7","end":"2014-05-29T23:20:28-04:00","children":[],"duration":1.002},{"name":"sql.active_record","payload":{"sql":"SELECT COUNT(*) FROM \"jobs\"  WHERE \"jobs\".\"status\" = 't' AND \"jobs\".\"category_id\" = 21","name":null,"connection_id":49242384,"binds":[],"line":161,"filename":"C:/Sites/work/tulkit/app/views/jobs/index.html.erb","method":"block (2 levels) in _app_views_jobs_index_html_erb___552676019_53062752"},"time":"2014-05-29T23:20:28-04:00","transaction_id":"534a8b4a7dabf06bc5b7","end":"2014-05-29T23:20:28-04:00","children":[],"duration":0.9990000000000001},{"name":"sql.active_record","payload":{"sql":"SELECT COUNT(*) FROM \"jobs\"  WHERE \"jobs\".\"status\" = 't' AND \"jobs\".\"category_id\" = 22","name":null,"connection_id":49242384,"binds":[],"line":161,"filename":"C:/Sites/work/tulkit/app/views/jobs/index.html.erb","method":"block (2 levels) in _app_views_jobs_index_html_erb___552676019_53062752"},"time":"2014-05-29T23:20:28-04:00","transaction_id":"534a8b4a7dabf06bc5b7","end":"2014-05-29T23:20:28-04:00","children":[],"duration":2.0},{"name":"sql.active_record","payload":{"sql":"SELECT COUNT(*) FROM \"jobs\"  WHERE \"jobs\".\"status\" = 't' AND \"jobs\".\"category_id\" = 19","binds":[],"name":"CACHE","connection_id":49242384,"line":189,"filename":"C:/Sites/work/tulkit/app/views/jobs/index.html.erb","method":"block in _app_views_jobs_index_html_erb___552676019_53062752"},"time":"2014-05-29T23:20:28-04:00","transaction_id":"0ae8f5e67693b087af12","end":"2014-05-29T23:20:28-04:00","children":[],"duration":1.002},{"name":"sql.active_record","payload":{"sql":"SELECT COUNT(*) FROM \"jobs\"  WHERE \"jobs\".\"status\" = 't' AND \"jobs\".\"category_id\" = 20","binds":[],"name":"CACHE","connection_id":49242384,"line":192,"filename":"C:/Sites/work/tulkit/app/views/jobs/index.html.erb","method":"block (2 levels) in _app_views_jobs_index_html_erb___552676019_53062752"},"time":"2014-05-29T23:20:28-04:00","transaction_id":"0ae8f5e67693b087af12","end":"2014-05-29T23:20:28-04:00","children":[],"duration":0.998},{"name":"sql.active_record","payload":{"sql":"SELECT COUNT(*) FROM \"jobs\"  WHERE \"jobs\".\"status\" = 't' AND \"jobs\".\"category_id\" = 21","binds":[],"name":"CACHE","connection_id":49242384,"line":192,"filename":"C:/Sites/work/tulkit/app/views/jobs/index.html.erb","method":"block (2 levels) in _app_views_jobs_index_html_erb___552676019_53062752"},"time":"2014-05-29T23:20:28-04:00","transaction_id":"0ae8f5e67693b087af12","end":"2014-05-29T23:20:28-04:00","children":[],"duration":0.998},{"name":"sql.active_record","payload":{"sql":"SELECT COUNT(*) FROM \"jobs\"  WHERE \"jobs\".\"status\" = 't' AND \"jobs\".\"category_id\" = 22","binds":[],"name":"CACHE","connection_id":49242384,"line":192,"filename":"C:/Sites/work/tulkit/app/views/jobs/index.html.erb","method":"block (2 levels) in _app_views_jobs_index_html_erb___552676019_53062752"},"time":"2014-05-29T23:20:28-04:00","transaction_id":"0ae8f5e67693b087af12","end":"2014-05-29T23:20:28-04:00","children":[],"duration":1.0},{"name":"sql.active_record","payload":{"sql":"SELECT COUNT(*) FROM \"jobs\"  WHERE \"jobs\".\"status\" = 't' AND \"jobs\".\"category_id\" = 23","name":null,"connection_id":49242384,"binds":[],"line":158,"filename":"C:/Sites/work/tulkit/app/views/jobs/index.html.erb","method":"block in _app_views_jobs_index_html_erb___552676019_53062752"},"time":"2014-05-29T23:20:28-04:00","transaction_id":"534a8b4a7dabf06bc5b7","end":"2014-05-29T23:20:28-04:00","children":[],"duration":1.002},{"name":"sql.active_record","payload":{"sql":"SELECT \"categories\".* FROM \"categories\"  WHERE \"categories\".\"parent_id\" = 23  ORDER BY \"categories\".\"lft\" ASC","name":"Category Load","connection_id":49242384,"binds":[],"line":160,"filename":"C:/Sites/work/tulkit/app/views/jobs/index.html.erb","method":"block in _app_views_jobs_index_html_erb___552676019_53062752"},"time":"2014-05-29T23:20:28-04:00","transaction_id":"534a8b4a7dabf06bc5b7","end":"2014-05-29T23:20:28-04:00","children":[],"duration":1.002},{"name":"sql.active_record","payload":{"sql":"SELECT COUNT(*) FROM \"jobs\"  WHERE \"jobs\".\"status\" = 't' AND \"jobs\".\"category_id\" = 23","binds":[],"name":"CACHE","connection_id":49242384,"line":189,"filename":"C:/Sites/work/tulkit/app/views/jobs/index.html.erb","method":"block in _app_views_jobs_index_html_erb___552676019_53062752"},"time":"2014-05-29T23:20:28-04:00","transaction_id":"0ae8f5e67693b087af12","end":"2014-05-29T23:20:28-04:00","children":[],"duration":1.001},{"name":"sql.active_record","payload":{"sql":"SELECT COUNT(*) FROM \"jobs\"  WHERE \"jobs\".\"status\" = 't' AND \"jobs\".\"category_id\" = 24","name":null,"connection_id":49242384,"binds":[],"line":158,"filename":"C:/Sites/work/tulkit/app/views/jobs/index.html.erb","method":"block in _app_views_jobs_index_html_erb___552676019_53062752"},"time":"2014-05-29T23:20:28-04:00","transaction_id":"534a8b4a7dabf06bc5b7","end":"2014-05-29T23:20:28-04:00","children":[],"duration":2.891},{"name":"sql.active_record","payload":{"sql":"SELECT \"categories\".* FROM \"categories\"  WHERE \"categories\".\"parent_id\" = 24  ORDER BY \"categories\".\"lft\" ASC","name":"Category Load","connection_id":49242384,"binds":[],"line":160,"filename":"C:/Sites/work/tulkit/app/views/jobs/index.html.erb","method":"block in _app_views_jobs_index_html_erb___552676019_53062752"},"time":"2014-05-29T23:20:28-04:00","transaction_id":"534a8b4a7dabf06bc5b7","end":"2014-05-29T23:20:28-04:00","children":[],"duration":1.001},{"name":"sql.active_record","payload":{"sql":"SELECT COUNT(*) FROM \"jobs\"  WHERE \"jobs\".\"status\" = 't' AND \"jobs\".\"category_id\" = 24","binds":[],"name":"CACHE","connection_id":49242384,"line":189,"filename":"C:/Sites/work/tulkit/app/views/jobs/index.html.erb","method":"block in _app_views_jobs_index_html_erb___552676019_53062752"},"time":"2014-05-29T23:20:28-04:00","transaction_id":"0ae8f5e67693b087af12","end":"2014-05-29T23:20:28-04:00","children":[],"duration":0.9990000000000001},{"name":"sql.active_record","payload":{"sql":"SELECT COUNT(*) FROM \"jobs\"  WHERE \"jobs\".\"status\" = 't' AND \"jobs\".\"category_id\" = 25","name":null,"connection_id":49242384,"binds":[],"line":158,"filename":"C:/Sites/work/tulkit/app/views/jobs/index.html.erb","method":"block in _app_views_jobs_index_html_erb___552676019_53062752"},"time":"2014-05-29T23:20:28-04:00","transaction_id":"534a8b4a7dabf06bc5b7","end":"2014-05-29T23:20:28-04:00","children":[],"duration":2.898},{"name":"sql.active_record","payload":{"sql":"SELECT \"categories\".* FROM \"categories\"  WHERE \"categories\".\"parent_id\" = 25  ORDER BY \"categories\".\"lft\" ASC","name":"Category Load","connection_id":49242384,"binds":[],"line":160,"filename":"C:/Sites/work/tulkit/app/views/jobs/index.html.erb","method":"block in _app_views_jobs_index_html_erb___552676019_53062752"},"time":"2014-05-29T23:20:28-04:00","transaction_id":"534a8b4a7dabf06bc5b7","end":"2014-05-29T23:20:28-04:00","children":[],"duration":1.915},{"name":"sql.active_record","payload":{"sql":"SELECT COUNT(*) FROM \"jobs\"  WHERE \"jobs\".\"status\" = 't' AND \"jobs\".\"category_id\" = 26","name":null,"connection_id":49242384,"binds":[],"line":161,"filename":"C:/Sites/work/tulkit/app/views/jobs/index.html.erb","method":"block (2 levels) in _app_views_jobs_index_html_erb___552676019_53062752"},"time":"2014-05-29T23:20:28-04:00","transaction_id":"534a8b4a7dabf06bc5b7","end":"2014-05-29T23:20:28-04:00","children":[],"duration":0.9990000000000001},{"name":"sql.active_record","payload":{"sql":"SELECT COUNT(*) FROM \"jobs\"  WHERE \"jobs\".\"status\" = 't' AND \"jobs\".\"category_id\" = 27","name":null,"connection_id":49242384,"binds":[],"line":161,"filename":"C:/Sites/work/tulkit/app/views/jobs/index.html.erb","method":"block (2 levels) in _app_views_jobs_index_html_erb___552676019_53062752"},"time":"2014-05-29T23:20:28-04:00","transaction_id":"534a8b4a7dabf06bc5b7","end":"2014-05-29T23:20:28-04:00","children":[],"duration":2.0},{"name":"sql.active_record","payload":{"sql":"SELECT COUNT(*) FROM \"jobs\"  WHERE \"jobs\".\"status\" = 't' AND \"jobs\".\"category_id\" = 28","name":null,"connection_id":49242384,"binds":[],"line":161,"filename":"C:/Sites/work/tulkit/app/views/jobs/index.html.erb","method":"block (2 levels) in _app_views_jobs_index_html_erb___552676019_53062752"},"time":"2014-05-29T23:20:28-04:00","transaction_id":"534a8b4a7dabf06bc5b7","end":"2014-05-29T23:20:28-04:00","children":[],"duration":1.002},{"name":"sql.active_record","payload":{"sql":"SELECT COUNT(*) FROM \"jobs\"  WHERE \"jobs\".\"status\" = 't' AND \"jobs\".\"category_id\" = 25","binds":[],"name":"CACHE","connection_id":49242384,"line":189,"filename":"C:/Sites/work/tulkit/app/views/jobs/index.html.erb","method":"block in _app_views_jobs_index_html_erb___552676019_53062752"},"time":"2014-05-29T23:20:28-04:00","transaction_id":"0ae8f5e67693b087af12","end":"2014-05-29T23:20:28-04:00","children":[],"duration":1.0},{"name":"sql.active_record","payload":{"sql":"SELECT COUNT(*) FROM \"jobs\"  WHERE \"jobs\".\"status\" = 't' AND \"jobs\".\"category_id\" = 26","binds":[],"name":"CACHE","connection_id":49242384,"line":192,"filename":"C:/Sites/work/tulkit/app/views/jobs/index.html.erb","method":"block (2 levels) in _app_views_jobs_index_html_erb___552676019_53062752"},"time":"2014-05-29T23:20:28-04:00","transaction_id":"0ae8f5e67693b087af12","end":"2014-05-29T23:20:28-04:00","children":[],"duration":1.0},{"name":"sql.active_record","payload":{"sql":"SELECT COUNT(*) FROM \"jobs\"  WHERE \"jobs\".\"status\" = 't' AND \"jobs\".\"category_id\" = 27","binds":[],"name":"CACHE","connection_id":49242384,"line":192,"filename":"C:/Sites/work/tulkit/app/views/jobs/index.html.erb","method":"block (2 levels) in _app_views_jobs_index_html_erb___552676019_53062752"},"time":"2014-05-29T23:20:28-04:00","transaction_id":"0ae8f5e67693b087af12","end":"2014-05-29T23:20:28-04:00","children":[],"duration":0.998},{"name":"sql.active_record","payload":{"sql":"SELECT COUNT(*) FROM \"jobs\"  WHERE \"jobs\".\"status\" = 't' AND \"jobs\".\"category_id\" = 28","binds":[],"name":"CACHE","connection_id":49242384,"line":192,"filename":"C:/Sites/work/tulkit/app/views/jobs/index.html.erb","method":"block (2 levels) in _app_views_jobs_index_html_erb___552676019_53062752"},"time":"2014-05-29T23:20:28-04:00","transaction_id":"0ae8f5e67693b087af12","end":"2014-05-29T23:20:28-04:00","children":[],"duration":0.9990000000000001},{"name":"sql.active_record","payload":{"sql":"SELECT COUNT(*) FROM \"jobs\"  WHERE \"jobs\".\"status\" = 't' AND \"jobs\".\"category_id\" = 29","name":null,"connection_id":49242384,"binds":[],"line":158,"filename":"C:/Sites/work/tulkit/app/views/jobs/index.html.erb","method":"block in _app_views_jobs_index_html_erb___552676019_53062752"},"time":"2014-05-29T23:20:28-04:00","transaction_id":"534a8b4a7dabf06bc5b7","end":"2014-05-29T23:20:28-04:00","children":[],"duration":2.004},{"name":"sql.active_record","payload":{"sql":"SELECT \"categories\".* FROM \"categories\"  WHERE \"categories\".\"parent_id\" = 29  ORDER BY \"categories\".\"lft\" ASC","name":"Category Load","connection_id":49242384,"binds":[],"line":160,"filename":"C:/Sites/work/tulkit/app/views/jobs/index.html.erb","method":"block in _app_views_jobs_index_html_erb___552676019_53062752"},"time":"2014-05-29T23:20:28-04:00","transaction_id":"534a8b4a7dabf06bc5b7","end":"2014-05-29T23:20:29-04:00","children":[],"duration":57.007000000000005},{"name":"sql.active_record","payload":{"sql":"SELECT COUNT(*) FROM \"jobs\"  WHERE \"jobs\".\"status\" = 't' AND \"jobs\".\"category_id\" = 29","binds":[],"name":"CACHE","connection_id":49242384,"line":189,"filename":"C:/Sites/work/tulkit/app/views/jobs/index.html.erb","method":"block in _app_views_jobs_index_html_erb___552676019_53062752"},"time":"2014-05-29T23:20:29-04:00","transaction_id":"0ae8f5e67693b087af12","end":"2014-05-29T23:20:29-04:00","children":[],"duration":0.0},{"name":"sql.active_record","payload":{"sql":"SELECT COUNT(*) FROM \"jobs\"  WHERE \"jobs\".\"status\" = 't' AND \"jobs\".\"category_id\" = 30","name":null,"connection_id":49242384,"binds":[],"line":158,"filename":"C:/Sites/work/tulkit/app/views/jobs/index.html.erb","method":"block in _app_views_jobs_index_html_erb___552676019_53062752"},"time":"2014-05-29T23:20:29-04:00","transaction_id":"534a8b4a7dabf06bc5b7","end":"2014-05-29T23:20:29-04:00","children":[],"duration":1.9200000000000002},{"name":"sql.active_record","payload":{"sql":"SELECT \"categories\".* FROM \"categories\"  WHERE \"categories\".\"parent_id\" = 30  ORDER BY \"categories\".\"lft\" ASC","name":"Category Load","connection_id":49242384,"binds":[],"line":160,"filename":"C:/Sites/work/tulkit/app/views/jobs/index.html.erb","method":"block in _app_views_jobs_index_html_erb___552676019_53062752"},"time":"2014-05-29T23:20:29-04:00","transaction_id":"534a8b4a7dabf06bc5b7","end":"2014-05-29T23:20:29-04:00","children":[],"duration":1.889},{"name":"sql.active_record","payload":{"sql":"SELECT COUNT(*) FROM \"jobs\"  WHERE \"jobs\".\"status\" = 't' AND \"jobs\".\"category_id\" = 30","binds":[],"name":"CACHE","connection_id":49242384,"line":189,"filename":"C:/Sites/work/tulkit/app/views/jobs/index.html.erb","method":"block in _app_views_jobs_index_html_erb___552676019_53062752"},"time":"2014-05-29T23:20:29-04:00","transaction_id":"0ae8f5e67693b087af12","end":"2014-05-29T23:20:29-04:00","children":[],"duration":0.998},{"name":"render_template.action_view","payload":{"identifier":"C:/Sites/work/tulkit/app/views/jobs/index.html.erb","layout":"layouts/application"},"time":"2014-05-29T23:20:28-04:00","transaction_id":"0ae8f5e67693b087af12","end":"2014-05-29T23:20:29-04:00","children":[],"duration":553.0699999999999},{"name":"sql.active_record","payload":{"sql":"SELECT  \"users\".* FROM \"users\"  WHERE \"users\".\"id\" = 3 LIMIT 1","binds":[],"name":"CACHE","connection_id":49242384,"line":41,"filename":"C:/Sites/work/tulkit/app/views/layouts/application.html.erb","method":"_app_views_layouts_application_html_erb___54920533_51916464"},"time":"2014-05-29T23:20:29-04:00","transaction_id":"0ae8f5e67693b087af12","end":"2014-05-29T23:20:29-04:00","children":[],"duration":0.9970000000000001},{"name":"sql.active_record","payload":{"sql":"SELECT  \"users\".* FROM \"users\"  WHERE \"users\".\"id\" = 3 LIMIT 1","binds":[],"name":"CACHE","connection_id":49242384,"line":41,"filename":"C:/Sites/work/tulkit/app/views/layouts/application.html.erb","method":"_app_views_layouts_application_html_erb___54920533_51916464"},"time":"2014-05-29T23:20:29-04:00","transaction_id":"0ae8f5e67693b087af12","end":"2014-05-29T23:20:29-04:00","children":[],"duration":1.002},{"name":"process_action.action_controller","payload":{"controller":"JobsController","action":"index","params":{"action":"index","controller":"jobs"},"format":"html","method":"GET","path":"/jobs","status":200,"view_runtime":583.0889999999999,"db_runtime":23.068},"time":"2014-05-29T23:20:28-04:00","transaction_id":"0ae8f5e67693b087af12","end":"2014-05-29T23:20:29-04:00","children":[],"duration":607.155}]